{
  "Version": 1,
  "ScreenId": "Register",
  "DisplayName": "注册界面",
  "BackgroundMusicAssetId": "",
  "Controls": [
    {
      "ControlId": "image",
      "DisplayName": "图片 10",
      "Kind": "Image",
      "X": 0,
      "Y": 0,
      "Width": 1920,
      "Height": 1080,
      "Anchor": "TopLeft",
      "IsLockedInEditor": true,
      "ZIndex": 10,
      "DragTargetControlIds": [],
      "MinimapLocalRangeScale": 1,
      "MinimapCompanionControlIds": [],
      "Text": "",
      "FontFamily": "NSimSun",
      "FontSize": 16,
      "TextColor": "#FFFFFF",
      "TextPosition": "TopLeft",
      "IsTextWrapEnabled": true,
      "TextEffect": {
        "IsOutlineEnabled": true,
        "OutlineColor": "#00000080",
        "OutlineWidth": 1,
        "IsShadowEnabled": true,
        "ShadowColor": "#000000",
        "ShadowOffsetX": 1,
        "ShadowOffsetY": 1,
        "ShadowBlur": 0
      },
      "AssetId": "Asset.3840x2160",
      "AssetIds": [
        "Asset.3840x2160"
      ],
      "ImageFramesPerSecond": 4,
      "ImageFillMode": "Fit",
      "ImageNineSlice": {
        "IsEnabled": false,
        "Left": 0,
        "Top": 0,
        "Right": 0,
        "Bottom": 0
      },
      "ResourceValueKind": "None",
      "ResourceFillMode": "VerticalOrb",
      "ResourcePreviewRatio": 0.75,
      "BackgroundColor": "",
      "InputBorderColor": "",
      "InputBorderWidth": 0,
      "InputCornerRadius": 0,
      "InputCaretColor": "",
      "InputTextOffsetX": 0,
      "InputTextOffsetY": 0,
      "InputCaretOffsetX": 0,
      "InputCaretOffsetY": 0,
      "CanHaveScrollbar": false,
      "ScrollTargetControlId": "",
      "ScrollbarButtonHeight": 18,
      "ScrollbarMinimumThumbHeight": 24,
      "ScrollbarTrackColor": "",
      "ScrollbarThumbColor": "",
      "ScrollbarButtonColor": "",
      "ScrollbarTrackAssetId": "",
      "ScrollbarThumbAssetId": "",
      "ScrollbarUpButtonAssetId": "",
      "ScrollbarDownButtonAssetId": "",
      "InputValueKind": "Text",
      "IsPasswordInput": false,
      "InputLineMode": "SingleLine",
      "InputMaxLength": 0,
      "HintText": "",
      "DefaultInputText": "",
      "CharacterSlotTexts": [],
      "CharacterPreviewAnimations": [],
      "ServerListItemHeight": 76,
      "ServerListItemSpacing": 10,
      "ServerListPreviewItemCount": 12,
      "ServerListItemDefaultStateStyle": {
        "AssetId": "",
        "BackgroundColor": "",
        "NineSlice": {
          "IsEnabled": false,
          "Left": 0,
          "Top": 0,
          "Right": 0,
          "Bottom": 0
        }
      },
      "ServerListItemSelectedStateStyle": {
        "AssetId": "",
        "BackgroundColor": "",
        "NineSlice": {
          "IsEnabled": false,
          "Left": 0,
          "Top": 0,
          "Right": 0,
          "Bottom": 0
        }
      },
      "ServerListItemDisabledStateStyle": {
        "AssetId": "",
        "BackgroundColor": "",
        "NineSlice": {
          "IsEnabled": false,
          "Left": 0,
          "Top": 0,
          "Right": 0,
          "Bottom": 0
        }
      },
      "ServerListItemElements": [],
      "InventoryGridCellWidth": 0,
      "InventoryGridCellHeight": 0,
      "InventoryGridColumnSpacing": 0,
      "InventoryGridRowSpacing": 0,
      "InventoryGridPaddingLeft": 0,
      "InventoryGridPaddingTop": 0,
      "InventoryGridPaddingRight": 0,
      "InventoryGridPaddingBottom": 0,
      "ContentTemplate": null,
      "ButtonTriggerKind": "SystemEvent",
      "ButtonSystemEvent": "CloseWindow",
      "ButtonScriptId": "",
      "ButtonTargetTemplateId": "",
      "ButtonOpenTargetKind": "ContentTemplate",
      "ButtonTargetFixedScreenId": "Inventory",
      "ButtonDefaultStateStyle": {
        "AssetId": "",
        "NineSlice": {
          "IsEnabled": false,
          "Left": 0,
          "Top": 0,
          "Right": 0,
          "Bottom": 0
        },
        "BackgroundColor": "",
        "HotAreaFeedbackColor": "",
        "HotAreaFeedbackOpacity": null,
        "HotAreaFeedbackFeatherRadius": null
      },
      "ButtonHoverStateStyle": {
        "AssetId": "",
        "NineSlice": {
          "IsEnabled": false,
          "Left": 0,
          "Top": 0,
          "Right": 0,
          "Bottom": 0
        },
        "BackgroundColor": "",
        "HotAreaFeedbackColor": "",
        "HotAreaFeedbackOpacity": null,
        "HotAreaFeedbackFeatherRadius": null
      },
      "ButtonPressedStateStyle": {
        "AssetId": "",
        "NineSlice": {
          "IsEnabled": false,
          "Left": 0,
          "Top": 0,
          "Right": 0,
          "Bottom": 0
        },
        "BackgroundColor": "",
        "HotAreaFeedbackColor": "",
        "HotAreaFeedbackOpacity": null,
        "HotAreaFeedbackFeatherRadius": null
      },
      "ButtonClickAreaX": 0,
      "ButtonClickAreaY": 0,
      "ButtonClickAreaWidth": 0,
      "ButtonClickAreaHeight": 0,
      "ButtonClickAreaCornerRadius": 0,
      "IsVisibleByDefault": true
    },
    {
      "ControlId": "image2",
      "DisplayName": "图片 11",
      "Kind": "Image",
      "X": 404,
      "Y": 254,
      "Width": 1040,
      "Height": 572,
      "Anchor": "TopLeft",
      "IsLockedInEditor": true,
      "ZIndex": 10,
      "DragTargetControlIds": [],
      "MinimapLocalRangeScale": 1,
      "MinimapCompanionControlIds": [],
      "Text": "",
      "FontFamily": "NSimSun",
      "FontSize": 16,
      "TextColor": "#FFFFFF",
      "TextPosition": "TopLeft",
      "IsTextWrapEnabled": true,
      "TextEffect": {
        "IsOutlineEnabled": true,
        "OutlineColor": "#00000080",
        "OutlineWidth": 1,
        "IsShadowEnabled": true,
        "ShadowColor": "#000000",
        "ShadowOffsetX": 1,
        "ShadowOffsetY": 1,
        "ShadowBlur": 0
      },
      "AssetId": "Asset.3840x2160_4",
      "AssetIds": [
        "Asset.3840x2160_4"
      ],
      "ImageFramesPerSecond": 4,
      "ImageFillMode": "Fit",
      "ImageNineSlice": {
        "IsEnabled": false,
        "Left": 0,
        "Top": 0,
        "Right": 0,
        "Bottom": 0
      },
      "ResourceValueKind": "None",
      "ResourceFillMode": "VerticalOrb",
      "ResourcePreviewRatio": 0.75,
      "BackgroundColor": "",
      "InputBorderColor": "",
      "InputBorderWidth": 0,
      "InputCornerRadius": 0,
      "InputCaretColor": "",
      "InputTextOffsetX": 0,
      "InputTextOffsetY": 0,
      "InputCaretOffsetX": 0,
      "InputCaretOffsetY": 0,
      "CanHaveScrollbar": false,
      "ScrollTargetControlId": "",
      "ScrollbarButtonHeight": 18,
      "ScrollbarMinimumThumbHeight": 24,
      "ScrollbarTrackColor": "",
      "ScrollbarThumbColor": "",
      "ScrollbarButtonColor": "",
      "ScrollbarTrackAssetId": "",
      "ScrollbarThumbAssetId": "",
      "ScrollbarUpButtonAssetId": "",
      "ScrollbarDownButtonAssetId": "",
      "InputValueKind": "Text",
      "IsPasswordInput": false,
      "InputLineMode": "SingleLine",
      "InputMaxLength": 0,
      "HintText": "",
      "DefaultInputText": "",
      "CharacterSlotTexts": [],
      "CharacterPreviewAnimations": [],
      "ServerListItemHeight": 76,
      "ServerListItemSpacing": 10,
      "ServerListPreviewItemCount": 12,
      "ServerListItemDefaultStateStyle": {
        "AssetId": "",
        "BackgroundColor": "",
        "NineSlice": {
          "IsEnabled": false,
          "Left": 0,
          "Top": 0,
          "Right": 0,
          "Bottom": 0
        }
      },
      "ServerListItemSelectedStateStyle": {
        "AssetId": "",
        "BackgroundColor": "",
        "NineSlice": {
          "IsEnabled": false,
          "Left": 0,
          "Top": 0,
          "Right": 0,
          "Bottom": 0
        }
      },
      "ServerListItemDisabledStateStyle": {
        "AssetId": "",
        "BackgroundColor": "",
        "NineSlice": {
          "IsEnabled": false,
          "Left": 0,
          "Top": 0,
          "Right": 0,
          "Bottom": 0
        }
      },
      "ServerListItemElements": [],
      "InventoryGridCellWidth": 0,
      "InventoryGridCellHeight": 0,
      "InventoryGridColumnSpacing": 0,
      "InventoryGridRowSpacing": 0,
      "InventoryGridPaddingLeft": 0,
      "InventoryGridPaddingTop": 0,
      "InventoryGridPaddingRight": 0,
      "InventoryGridPaddingBottom": 0,
      "ContentTemplate": null,
      "ButtonTriggerKind": "SystemEvent",
      "ButtonSystemEvent": "CloseWindow",
      "ButtonScriptId": "",
      "ButtonTargetTemplateId": "",
      "ButtonOpenTargetKind": "ContentTemplate",
      "ButtonTargetFixedScreenId": "Inventory",
      "ButtonDefaultStateStyle": {
        "AssetId": "",
        "NineSlice": {
          "IsEnabled": false,
          "Left": 0,
          "Top": 0,
          "Right": 0,
          "Bottom": 0
        },
        "BackgroundColor": "",
        "HotAreaFeedbackColor": "",
        "HotAreaFeedbackOpacity": null,
        "HotAreaFeedbackFeatherRadius": null
      },
      "ButtonHoverStateStyle": {
        "AssetId": "",
        "NineSlice": {
          "IsEnabled": false,
          "Left": 0,
          "Top": 0,
          "Right": 0,
          "Bottom": 0
        },
        "BackgroundColor": "",
        "HotAreaFeedbackColor": "",
        "HotAreaFeedbackOpacity": null,
        "HotAreaFeedbackFeatherRadius": null
      },
      "ButtonPressedStateStyle": {
        "AssetId": "",
        "NineSlice": {
          "IsEnabled": false,
          "Left": 0,
          "Top": 0,
          "Right": 0,
          "Bottom": 0
        },
        "BackgroundColor": "",
        "HotAreaFeedbackColor": "",
        "HotAreaFeedbackOpacity": null,
        "HotAreaFeedbackFeatherRadius": null
      },
      "ButtonClickAreaX": 0,
      "ButtonClickAreaY": 0,
      "ButtonClickAreaWidth": 0,
      "ButtonClickAreaHeight": 0,
      "ButtonClickAreaCornerRadius": 0,
      "IsVisibleByDefault": true
    },
    {
      "ControlId": "registerPasswordInput",
      "DisplayName": "密码输入框",
      "Kind": "Input",
      "X": 650,
      "Y": 472,
      "Width": 261,
      "Height": 42,
      "Anchor": "TopLeft",
      "IsLockedInEditor": true,
      "ZIndex": 11,
      "DragTargetControlIds": [],
      "MinimapLocalRangeScale": 1,
      "MinimapCompanionControlIds": [],
      "Text": "",
      "FontFamily": "NSimSun",
      "FontSize": 16,
      "TextColor": "#FFFFFF",
      "TextPosition": "TopLeft",
      "IsTextWrapEnabled": false,
      "TextEffect": {
        "IsOutlineEnabled": true,
        "OutlineColor": "#00000080",
        "OutlineWidth": 1,
        "IsShadowEnabled": true,
        "ShadowColor": "#000000",
        "ShadowOffsetX": 1,
        "ShadowOffsetY": 1,
        "ShadowBlur": 0
      },
      "AssetId": "",
      "AssetIds": [],
      "ImageFramesPerSecond": 4,
      "ImageFillMode": "Fit",
      "ImageNineSlice": {
        "IsEnabled": false,
        "Left": 0,
        "Top": 0,
        "Right": 0,
        "Bottom": 0
      },
      "ResourceValueKind": "None",
      "ResourceFillMode": "VerticalOrb",
      "ResourcePreviewRatio": 0.75,
      "BackgroundColor": "#10182099",
      "InputBorderColor": "#7A8994",
      "InputBorderWidth": 1,
      "InputCornerRadius": 6,
      "InputCaretColor": "#DABE6CE6",
      "InputTextOffsetX": 0,
      "InputTextOffsetY": 0,
      "InputCaretOffsetX": 0,
      "InputCaretOffsetY": 0,
      "CanHaveScrollbar": false,
      "ScrollTargetControlId": "",
      "ScrollbarButtonHeight": 18,
      "ScrollbarMinimumThumbHeight": 24,
      "ScrollbarTrackColor": "#0C1520CC",
      "ScrollbarThumbColor": "#7A8994",
      "ScrollbarButtonColor": "#223344CC",
      "ScrollbarTrackAssetId": "",
      "ScrollbarThumbAssetId": "",
      "ScrollbarUpButtonAssetId": "",
      "ScrollbarDownButtonAssetId": "",
      "InputValueKind": "Text",
      "IsPasswordInput": true,
      "InputLineMode": "SingleLine",
      "InputMaxLength": 20,
      "HintText": "请输入密码",
      "DefaultInputText": "",
      "CharacterSlotTexts": [],
      "CharacterPreviewAnimations": [],
      "ServerListItemHeight": 76,
      "ServerListItemSpacing": 10,
      "ServerListPreviewItemCount": 12,
      "ServerListItemDefaultStateStyle": {
        "AssetId": "",
        "BackgroundColor": "",
        "NineSlice": {
          "IsEnabled": false,
          "Left": 0,
          "Top": 0,
          "Right": 0,
          "Bottom": 0
        }
      },
      "ServerListItemSelectedStateStyle": {
        "AssetId": "",
        "BackgroundColor": "",
        "NineSlice": {
          "IsEnabled": false,
          "Left": 0,
          "Top": 0,
          "Right": 0,
          "Bottom": 0
        }
      },
      "ServerListItemDisabledStateStyle": {
        "AssetId": "",
        "BackgroundColor": "",
        "NineSlice": {
          "IsEnabled": false,
          "Left": 0,
          "Top": 0,
          "Right": 0,
          "Bottom": 0
        }
      },
      "ServerListItemElements": [],
      "InventoryGridCellWidth": 0,
      "InventoryGridCellHeight": 0,
      "InventoryGridColumnSpacing": 0,
      "InventoryGridRowSpacing": 0,
      "InventoryGridPaddingLeft": 0,
      "InventoryGridPaddingTop": 0,
      "InventoryGridPaddingRight": 0,
      "InventoryGridPaddingBottom": 0,
      "ContentTemplate": null,
      "ButtonTriggerKind": "SystemEvent",
      "ButtonSystemEvent": "CloseWindow",
      "ButtonScriptId": "",
      "ButtonTargetTemplateId": "",
      "ButtonOpenTargetKind": "ContentTemplate",
      "ButtonTargetFixedScreenId": "Inventory",
      "ButtonDefaultStateStyle": {
        "AssetId": "",
        "NineSlice": {
          "IsEnabled": false,
          "Left": 0,
          "Top": 0,
          "Right": 0,
          "Bottom": 0
        },
        "BackgroundColor": "",
        "HotAreaFeedbackColor": "",
        "HotAreaFeedbackOpacity": null,
        "HotAreaFeedbackFeatherRadius": null
      },
      "ButtonHoverStateStyle": {
        "AssetId": "",
        "NineSlice": {
          "IsEnabled": false,
          "Left": 0,
          "Top": 0,
          "Right": 0,
          "Bottom": 0
        },
        "BackgroundColor": "",
        "HotAreaFeedbackColor": "",
        "HotAreaFeedbackOpacity": null,
        "HotAreaFeedbackFeatherRadius": null
      },
      "ButtonPressedStateStyle": {
        "AssetId": "",
        "NineSlice": {
          "IsEnabled": false,
          "Left": 0,
          "Top": 0,
          "Right": 0,
          "Bottom": 0
        },
        "BackgroundColor": "",
        "HotAreaFeedbackColor": "",
        "HotAreaFeedbackOpacity": null,
        "HotAreaFeedbackFeatherRadius": null
      },
      "ButtonClickAreaX": 0,
      "ButtonClickAreaY": 0,
      "ButtonClickAreaWidth": 0,
      "ButtonClickAreaHeight": 0,
      "ButtonClickAreaCornerRadius": 0,
      "IsVisibleByDefault": true
    },
    {
      "ControlId": "registerConfirmPasswordInput",
      "DisplayName": "确认密码输入框",
      "Kind": "Input",
      "X": 650,
      "Y": 538,
      "Width": 261,
      "Height": 42,
      "Anchor": "TopLeft",
      "IsLockedInEditor": false,
      "ZIndex": 12,
      "DragTargetControlIds": [],
      "MinimapLocalRangeScale": 1,
      "MinimapCompanionControlIds": [],
      "Text": "",
      "FontFamily": "NSimSun",
      "FontSize": 16,
      "TextColor": "#FFFFFF",
      "TextPosition": "TopLeft",
      "IsTextWrapEnabled": false,
      "TextEffect": {
        "IsOutlineEnabled": true,
        "OutlineColor": "#00000080",
        "OutlineWidth": 1,
        "IsShadowEnabled": true,
        "ShadowColor": "#000000",
        "ShadowOffsetX": 1,
        "ShadowOffsetY": 1,
        "ShadowBlur": 0
      },
      "AssetId": "",
      "AssetIds": [],
      "ImageFramesPerSecond": 4,
      "ImageFillMode": "Fit",
      "ImageNineSlice": {
        "IsEnabled": false,
        "Left": 0,
        "Top": 0,
        "Right": 0,
        "Bottom": 0
      },
      "ResourceValueKind": "None",
      "ResourceFillMode": "VerticalOrb",
      "ResourcePreviewRatio": 0.75,
      "BackgroundColor": "#10182099",
      "InputBorderColor": "#7A8994",
      "InputBorderWidth": 1,
      "InputCornerRadius": 6,
      "InputCaretColor": "#DABE6CE6",
      "InputTextOffsetX": 0,
      "InputTextOffsetY": 0,
      "InputCaretOffsetX": 0,
      "InputCaretOffsetY": 0,
      "CanHaveScrollbar": false,
      "ScrollTargetControlId": "",
      "ScrollbarButtonHeight": 18,
      "ScrollbarMinimumThumbHeight": 24,
      "ScrollbarTrackColor": "#0C1520CC",
      "ScrollbarThumbColor": "#7A8994",
      "ScrollbarButtonColor": "#223344CC",
      "ScrollbarTrackAssetId": "",
      "ScrollbarThumbAssetId": "",
      "ScrollbarUpButtonAssetId": "",
      "ScrollbarDownButtonAssetId": "",
      "InputValueKind": "Text",
      "IsPasswordInput": true,
      "InputLineMode": "SingleLine",
      "InputMaxLength": 20,
      "HintText": "请再次输入密码",
      "DefaultInputText": "",
      "CharacterSlotTexts": [],
      "CharacterPreviewAnimations": [],
      "ServerListItemHeight": 76,
      "ServerListItemSpacing": 10,
      "ServerListPreviewItemCount": 12,
      "ServerListItemDefaultStateStyle": {
        "AssetId": "",
        "BackgroundColor": "",
        "NineSlice": {
          "IsEnabled": false,
          "Left": 0,
          "Top": 0,
          "Right": 0,
          "Bottom": 0
        }
      },
      "ServerListItemSelectedStateStyle": {
        "AssetId": "",
        "BackgroundColor": "",
        "NineSlice": {
          "IsEnabled": false,
          "Left": 0,
          "Top": 0,
          "Right": 0,
          "Bottom": 0
        }
      },
      "ServerListItemDisabledStateStyle": {
        "AssetId": "",
        "BackgroundColor": "",
        "NineSlice": {
          "IsEnabled": false,
          "Left": 0,
          "Top": 0,
          "Right": 0,
          "Bottom": 0
        }
      },
      "ServerListItemElements": [],
      "InventoryGridCellWidth": 0,
      "InventoryGridCellHeight": 0,
      "InventoryGridColumnSpacing": 0,
      "InventoryGridRowSpacing": 0,
      "InventoryGridPaddingLeft": 0,
      "InventoryGridPaddingTop": 0,
      "InventoryGridPaddingRight": 0,
      "InventoryGridPaddingBottom": 0,
      "ContentTemplate": null,
      "ButtonTriggerKind": "SystemEvent",
      "ButtonSystemEvent": "CloseWindow",
      "ButtonScriptId": "",
      "ButtonTargetTemplateId": "",
      "ButtonOpenTargetKind": "ContentTemplate",
      "ButtonTargetFixedScreenId": "Inventory",
      "ButtonDefaultStateStyle": {
        "AssetId": "",
        "NineSlice": {
          "IsEnabled": false,
          "Left": 0,
          "Top": 0,
          "Right": 0,
          "Bottom": 0
        },
        "BackgroundColor": "",
        "HotAreaFeedbackColor": "",
        "HotAreaFeedbackOpacity": null,
        "HotAreaFeedbackFeatherRadius": null
      },
      "ButtonHoverStateStyle": {
        "AssetId": "",
        "NineSlice": {
          "IsEnabled": false,
          "Left": 0,
          "Top": 0,
          "Right": 0,
          "Bottom": 0
        },
        "BackgroundColor": "",
        "HotAreaFeedbackColor": "",
        "HotAreaFeedbackOpacity": null,
        "HotAreaFeedbackFeatherRadius": null
      },
      "ButtonPressedStateStyle": {
        "AssetId": "",
        "NineSlice": {
          "IsEnabled": false,
          "Left": 0,
          "Top": 0,
          "Right": 0,
          "Bottom": 0
        },
        "BackgroundColor": "",
        "HotAreaFeedbackColor": "",
        "HotAreaFeedbackOpacity": null,
        "HotAreaFeedbackFeatherRadius": null
      },
      "ButtonClickAreaX": 0,
      "ButtonClickAreaY": 0,
      "ButtonClickAreaWidth": 0,
      "ButtonClickAreaHeight": 0,
      "ButtonClickAreaCornerRadius": 0,
      "IsVisibleByDefault": true
    },
    {
      "ControlId": "registerAccountInput",
      "DisplayName": "账号输入框",
      "Kind": "Input",
      "X": 650,
      "Y": 406,
      "Width": 261,
      "Height": 42,
      "Anchor": "TopLeft",
      "IsLockedInEditor": true,
      "ZIndex": 13,
      "DragTargetControlIds": [],
      "MinimapLocalRangeScale": 1,
      "MinimapCompanionControlIds": [],
      "Text": "",
      "FontFamily": "NSimSun",
      "FontSize": 16,
      "TextColor": "#FFFFFF",
      "TextPosition": "TopLeft",
      "IsTextWrapEnabled": false,
      "TextEffect": {
        "IsOutlineEnabled": true,
        "OutlineColor": "#00000080",
        "OutlineWidth": 1,
        "IsShadowEnabled": true,
        "ShadowColor": "#000000",
        "ShadowOffsetX": 1,
        "ShadowOffsetY": 1,
        "ShadowBlur": 0
      },
      "AssetId": "",
      "AssetIds": [],
      "ImageFramesPerSecond": 4,
      "ImageFillMode": "Fit",
      "ImageNineSlice": {
        "IsEnabled": false,
        "Left": 0,
        "Top": 0,
        "Right": 0,
        "Bottom": 0
      },
      "ResourceValueKind": "None",
      "ResourceFillMode": "VerticalOrb",
      "ResourcePreviewRatio": 0.75,
      "BackgroundColor": "#10182099",
      "InputBorderColor": "#7A8994",
      "InputBorderWidth": 1,
      "InputCornerRadius": 6,
      "InputCaretColor": "#DABE6CE6",
      "InputTextOffsetX": 0,
      "InputTextOffsetY": 0,
      "InputCaretOffsetX": 0,
      "InputCaretOffsetY": 0,
      "CanHaveScrollbar": false,
      "ScrollTargetControlId": "",
      "ScrollbarButtonHeight": 18,
      "ScrollbarMinimumThumbHeight": 24,
      "ScrollbarTrackColor": "#0C1520CC",
      "ScrollbarThumbColor": "#7A8994",
      "ScrollbarButtonColor": "#223344CC",
      "ScrollbarTrackAssetId": "",
      "ScrollbarThumbAssetId": "",
      "ScrollbarUpButtonAssetId": "",
      "ScrollbarDownButtonAssetId": "",
      "InputValueKind": "Text",
      "IsPasswordInput": false,
      "InputLineMode": "SingleLine",
      "InputMaxLength": 20,
      "HintText": "请输入账号",
      "DefaultInputText": "",
      "CharacterSlotTexts": [],
      "CharacterPreviewAnimations": [],
      "ServerListItemHeight": 76,
      "ServerListItemSpacing": 10,
      "ServerListPreviewItemCount": 12,
      "ServerListItemDefaultStateStyle": {
        "AssetId": "",
        "BackgroundColor": "",
        "NineSlice": {
          "IsEnabled": false,
          "Left": 0,
          "Top": 0,
          "Right": 0,
          "Bottom": 0
        }
      },
      "ServerListItemSelectedStateStyle": {
        "AssetId": "",
        "BackgroundColor": "",
        "NineSlice": {
          "IsEnabled": false,
          "Left": 0,
          "Top": 0,
          "Right": 0,
          "Bottom": 0
        }
      },
      "ServerListItemDisabledStateStyle": {
        "AssetId": "",
        "BackgroundColor": "",
        "NineSlice": {
          "IsEnabled": false,
          "Left": 0,
          "Top": 0,
          "Right": 0,
          "Bottom": 0
        }
      },
      "ServerListItemElements": [],
      "InventoryGridCellWidth": 0,
      "InventoryGridCellHeight": 0,
      "InventoryGridColumnSpacing": 0,
      "InventoryGridRowSpacing": 0,
      "InventoryGridPaddingLeft": 0,
      "InventoryGridPaddingTop": 0,
      "InventoryGridPaddingRight": 0,
      "InventoryGridPaddingBottom": 0,
      "ContentTemplate": null,
      "ButtonTriggerKind": "SystemEvent",
      "ButtonSystemEvent": "CloseWindow",
      "ButtonScriptId": "",
      "ButtonTargetTemplateId": "",
      "ButtonOpenTargetKind": "ContentTemplate",
      "ButtonTargetFixedScreenId": "Inventory",
      "ButtonDefaultStateStyle": {
        "AssetId": "",
        "NineSlice": {
          "IsEnabled": false,
          "Left": 0,
          "Top": 0,
          "Right": 0,
          "Bottom": 0
        },
        "BackgroundColor": "",
        "HotAreaFeedbackColor": "",
        "HotAreaFeedbackOpacity": null,
        "HotAreaFeedbackFeatherRadius": null
      },
      "ButtonHoverStateStyle": {
        "AssetId": "",
        "NineSlice": {
          "IsEnabled": false,
          "Left": 0,
          "Top": 0,
          "Right": 0,
          "Bottom": 0
        },
        "BackgroundColor": "",
        "HotAreaFeedbackColor": "",
        "HotAreaFeedbackOpacity": null,
        "HotAreaFeedbackFeatherRadius": null
      },
      "ButtonPressedStateStyle": {
        "AssetId": "",
        "NineSlice": {
          "IsEnabled": false,
          "Left": 0,
          "Top": 0,
          "Right": 0,
          "Bottom": 0
        },
        "BackgroundColor": "",
        "HotAreaFeedbackColor": "",
        "HotAreaFeedbackOpacity": null,
        "HotAreaFeedbackFeatherRadius": null
      },
      "ButtonClickAreaX": 0,
      "ButtonClickAreaY": 0,
      "ButtonClickAreaWidth": 0,
      "ButtonClickAreaHeight": 0,
      "ButtonClickAreaCornerRadius": 0,
      "IsVisibleByDefault": true
    },
    {
      "ControlId": "registerQuestion1Input",
      "DisplayName": "问题1输入框",
      "Kind": "Input",
      "X": 651,
      "Y": 603,
      "Width": 258,
      "Height": 42,
      "Anchor": "TopLeft",
      "IsLockedInEditor": true,
      "ZIndex": 13,
      "DragTargetControlIds": [],
      "MinimapLocalRangeScale": 1,
      "MinimapCompanionControlIds": [],
      "Text": "",
      "FontFamily": "NSimSun",
      "FontSize": 16,
      "TextColor": "#FFFFFF",
      "TextPosition": "TopLeft",
      "IsTextWrapEnabled": false,
      "TextEffect": {
        "IsOutlineEnabled": true,
        "OutlineColor": "#00000080",
        "OutlineWidth": 1,
        "IsShadowEnabled": true,
        "ShadowColor": "#000000",
        "ShadowOffsetX": 1,
        "ShadowOffsetY": 1,
        "ShadowBlur": 0
      },
      "AssetId": "",
      "AssetIds": [],
      "ImageFramesPerSecond": 4,
      "ImageFillMode": "Fit",
      "ImageNineSlice": {
        "IsEnabled": false,
        "Left": 0,
        "Top": 0,
        "Right": 0,
        "Bottom": 0
      },
      "ResourceValueKind": "None",
      "ResourceFillMode": "VerticalOrb",
      "ResourcePreviewRatio": 0.75,
      "BackgroundColor": "#10182099",
      "InputBorderColor": "#7A8994",
      "InputBorderWidth": 1,
      "InputCornerRadius": 6,
      "InputCaretColor": "#DABE6CE6",
      "InputTextOffsetX": 0,
      "InputTextOffsetY": 0,
      "InputCaretOffsetX": 0,
      "InputCaretOffsetY": 0,
      "CanHaveScrollbar": false,
      "ScrollTargetControlId": "",
      "ScrollbarButtonHeight": 18,
      "ScrollbarMinimumThumbHeight": 24,
      "ScrollbarTrackColor": "#0C1520CC",
      "ScrollbarThumbColor": "#7A8994",
      "ScrollbarButtonColor": "#223344CC",
      "ScrollbarTrackAssetId": "",
      "ScrollbarThumbAssetId": "",
      "ScrollbarUpButtonAssetId": "",
      "ScrollbarDownButtonAssetId": "",
      "InputValueKind": "Text",
      "IsPasswordInput": false,
      "InputLineMode": "SingleLine",
      "InputMaxLength": 20,
      "HintText": "请输入问题1",
      "DefaultInputText": "",
      "CharacterSlotTexts": [],
      "CharacterPreviewAnimations": [],
      "ServerListItemHeight": 76,
      "ServerListItemSpacing": 10,
      "ServerListPreviewItemCount": 12,
      "ServerListItemDefaultStateStyle": {
        "AssetId": "",
        "BackgroundColor": "",
        "NineSlice": {
          "IsEnabled": false,
          "Left": 0,
          "Top": 0,
          "Right": 0,
          "Bottom": 0
        }
      },
      "ServerListItemSelectedStateStyle": {
        "AssetId": "",
        "BackgroundColor": "",
        "NineSlice": {
          "IsEnabled": false,
          "Left": 0,
          "Top": 0,
          "Right": 0,
          "Bottom": 0
        }
      },
      "ServerListItemDisabledStateStyle": {
        "AssetId": "",
        "BackgroundColor": "",
        "NineSlice": {
          "IsEnabled": false,
          "Left": 0,
          "Top": 0,
          "Right": 0,
          "Bottom": 0
        }
      },
      "ServerListItemElements": [],
      "InventoryGridCellWidth": 0,
      "InventoryGridCellHeight": 0,
      "InventoryGridColumnSpacing": 0,
      "InventoryGridRowSpacing": 0,
      "InventoryGridPaddingLeft": 0,
      "InventoryGridPaddingTop": 0,
      "InventoryGridPaddingRight": 0,
      "InventoryGridPaddingBottom": 0,
      "ContentTemplate": null,
      "ButtonTriggerKind": "SystemEvent",
      "ButtonSystemEvent": "CloseWindow",
      "ButtonScriptId": "",
      "ButtonTargetTemplateId": "",
      "ButtonOpenTargetKind": "ContentTemplate",
      "ButtonTargetFixedScreenId": "Inventory",
      "ButtonDefaultStateStyle": {
        "AssetId": "",
        "NineSlice": {
          "IsEnabled": false,
          "Left": 0,
          "Top": 0,
          "Right": 0,
          "Bottom": 0
        },
        "BackgroundColor": "",
        "HotAreaFeedbackColor": "",
        "HotAreaFeedbackOpacity": null,
        "HotAreaFeedbackFeatherRadius": null
      },
      "ButtonHoverStateStyle": {
        "AssetId": "",
        "NineSlice": {
          "IsEnabled": false,
          "Left": 0,
          "Top": 0,
          "Right": 0,
          "Bottom": 0
        },
        "BackgroundColor": "",
        "HotAreaFeedbackColor": "",
        "HotAreaFeedbackOpacity": null,
        "HotAreaFeedbackFeatherRadius": null
      },
      "ButtonPressedStateStyle": {
        "AssetId": "",
        "NineSlice": {
          "IsEnabled": false,
          "Left": 0,
          "Top": 0,
          "Right": 0,
          "Bottom": 0
        },
        "BackgroundColor": "",
        "HotAreaFeedbackColor": "",
        "HotAreaFeedbackOpacity": null,
        "HotAreaFeedbackFeatherRadius": null
      },
      "ButtonClickAreaX": 0,
      "ButtonClickAreaY": 0,
      "ButtonClickAreaWidth": 0,
      "ButtonClickAreaHeight": 0,
      "ButtonClickAreaCornerRadius": 0,
      "IsVisibleByDefault": true
    },
    {
      "ControlId": "registerAnswer1Input",
      "DisplayName": "答案1输入框",
      "Kind": "Input",
      "X": 1057,
      "Y": 439,
      "Width": 251,
      "Height": 42,
      "Anchor": "TopLeft",
      "IsLockedInEditor": true,
      "ZIndex": 14,
      "DragTargetControlIds": [],
      "MinimapLocalRangeScale": 1,
      "MinimapCompanionControlIds": [],
      "Text": "",
      "FontFamily": "NSimSun",
      "FontSize": 16,
      "TextColor": "#FFFFFF",
      "TextPosition": "TopLeft",
      "IsTextWrapEnabled": false,
      "TextEffect": {
        "IsOutlineEnabled": true,
        "OutlineColor": "#00000080",
        "OutlineWidth": 1,
        "IsShadowEnabled": true,
        "ShadowColor": "#000000",
        "ShadowOffsetX": 1,
        "ShadowOffsetY": 1,
        "ShadowBlur": 0
      },
      "AssetId": "",
      "AssetIds": [],
      "ImageFramesPerSecond": 4,
      "ImageFillMode": "Fit",
      "ImageNineSlice": {
        "IsEnabled": false,
        "Left": 0,
        "Top": 0,
        "Right": 0,
        "Bottom": 0
      },
      "ResourceValueKind": "None",
      "ResourceFillMode": "VerticalOrb",
      "ResourcePreviewRatio": 0.75,
      "BackgroundColor": "#10182099",
      "InputBorderColor": "#7A8994",
      "InputBorderWidth": 1,
      "InputCornerRadius": 6,
      "InputCaretColor": "#DABE6CE6",
      "InputTextOffsetX": 0,
      "InputTextOffsetY": 0,
      "InputCaretOffsetX": 0,
      "InputCaretOffsetY": 0,
      "CanHaveScrollbar": false,
      "ScrollTargetControlId": "",
      "ScrollbarButtonHeight": 18,
      "ScrollbarMinimumThumbHeight": 24,
      "ScrollbarTrackColor": "#0C1520CC",
      "ScrollbarThumbColor": "#7A8994",
      "ScrollbarButtonColor": "#223344CC",
      "ScrollbarTrackAssetId": "",
      "ScrollbarThumbAssetId": "",
      "ScrollbarUpButtonAssetId": "",
      "ScrollbarDownButtonAssetId": "",
      "InputValueKind": "Text",
      "IsPasswordInput": false,
      "InputLineMode": "SingleLine",
      "InputMaxLength": 20,
      "HintText": "请输入答案1",
      "DefaultInputText": "",
      "CharacterSlotTexts": [],
      "CharacterPreviewAnimations": [],
      "ServerListItemHeight": 76,
      "ServerListItemSpacing": 10,
      "ServerListPreviewItemCount": 12,
      "ServerListItemDefaultStateStyle": {
        "AssetId": "",
        "BackgroundColor": "",
        "NineSlice": {
          "IsEnabled": false,
          "Left": 0,
          "Top": 0,
          "Right": 0,
          "Bottom": 0
        }
      },
      "ServerListItemSelectedStateStyle": {
        "AssetId": "",
        "BackgroundColor": "",
        "NineSlice": {
          "IsEnabled": false,
          "Left": 0,
          "Top": 0,
          "Right": 0,
          "Bottom": 0
        }
      },
      "ServerListItemDisabledStateStyle": {
        "AssetId": "",
        "BackgroundColor": "",
        "NineSlice": {
          "IsEnabled": false,
          "Left": 0,
          "Top": 0,
          "Right": 0,
          "Bottom": 0
        }
      },
      "ServerListItemElements": [],
      "InventoryGridCellWidth": 0,
      "InventoryGridCellHeight": 0,
      "InventoryGridColumnSpacing": 0,
      "InventoryGridRowSpacing": 0,
      "InventoryGridPaddingLeft": 0,
      "InventoryGridPaddingTop": 0,
      "InventoryGridPaddingRight": 0,
      "InventoryGridPaddingBottom": 0,
      "ContentTemplate": null,
      "ButtonTriggerKind": "SystemEvent",
      "ButtonSystemEvent": "CloseWindow",
      "ButtonScriptId": "",
      "ButtonTargetTemplateId": "",
      "ButtonOpenTargetKind": "ContentTemplate",
      "ButtonTargetFixedScreenId": "Inventory",
      "ButtonDefaultStateStyle": {
        "AssetId": "",
        "NineSlice": {
          "IsEnabled": false,
          "Left": 0,
          "Top": 0,
          "Right": 0,
          "Bottom": 0
        },
        "BackgroundColor": "",
        "HotAreaFeedbackColor": "",
        "HotAreaFeedbackOpacity": null,
        "HotAreaFeedbackFeatherRadius": null
      },
      "ButtonHoverStateStyle": {
        "AssetId": "",
        "NineSlice": {
          "IsEnabled": false,
          "Left": 0,
          "Top": 0,
          "Right": 0,
          "Bottom": 0
        },
        "BackgroundColor": "",
        "HotAreaFeedbackColor": "",
        "HotAreaFeedbackOpacity": null,
        "HotAreaFeedbackFeatherRadius": null
      },
      "ButtonPressedStateStyle": {
        "AssetId": "",
        "NineSlice": {
          "IsEnabled": false,
          "Left": 0,
          "Top": 0,
          "Right": 0,
          "Bottom": 0
        },
        "BackgroundColor": "",
        "HotAreaFeedbackColor": "",
        "HotAreaFeedbackOpacity": null,
        "HotAreaFeedbackFeatherRadius": null
      },
      "ButtonClickAreaX": 0,
      "ButtonClickAreaY": 0,
      "ButtonClickAreaWidth": 0,
      "ButtonClickAreaHeight": 0,
      "ButtonClickAreaCornerRadius": 0,
      "IsVisibleByDefault": true
    },
    {
      "ControlId": "registerQuestion2Input",
      "DisplayName": "问题2输入框",
      "Kind": "Input",
      "X": 1058,
      "Y": 506,
      "Width": 251,
      "Height": 42,
      "Anchor": "TopLeft",
      "IsLockedInEditor": true,
      "ZIndex": 15,
      "DragTargetControlIds": [],
      "MinimapLocalRangeScale": 1,
      "MinimapCompanionControlIds": [],
      "Text": "",
      "FontFamily": "NSimSun",
      "FontSize": 16,
      "TextColor": "#FFFFFF",
      "TextPosition": "TopLeft",
      "IsTextWrapEnabled": false,
      "TextEffect": {
        "IsOutlineEnabled": true,
        "OutlineColor": "#00000080",
        "OutlineWidth": 1,
        "IsShadowEnabled": true,
        "ShadowColor": "#000000",
        "ShadowOffsetX": 1,
        "ShadowOffsetY": 1,
        "ShadowBlur": 0
      },
      "AssetId": "",
      "AssetIds": [],
      "ImageFramesPerSecond": 4,
      "ImageFillMode": "Fit",
      "ImageNineSlice": {
        "IsEnabled": false,
        "Left": 0,
        "Top": 0,
        "Right": 0,
        "Bottom": 0
      },
      "ResourceValueKind": "None",
      "ResourceFillMode": "VerticalOrb",
      "ResourcePreviewRatio": 0.75,
      "BackgroundColor": "#10182099",
      "InputBorderColor": "#7A8994",
      "InputBorderWidth": 1,
      "InputCornerRadius": 6,
      "InputCaretColor": "#DABE6CE6",
      "InputTextOffsetX": 0,
      "InputTextOffsetY": 0,
      "InputCaretOffsetX": 0,
      "InputCaretOffsetY": 0,
      "CanHaveScrollbar": false,
      "ScrollTargetControlId": "",
      "ScrollbarButtonHeight": 18,
      "ScrollbarMinimumThumbHeight": 24,
      "ScrollbarTrackColor": "#0C1520CC",
      "ScrollbarThumbColor": "#7A8994",
      "ScrollbarButtonColor": "#223344CC",
      "ScrollbarTrackAssetId": "",
      "ScrollbarThumbAssetId": "",
      "ScrollbarUpButtonAssetId": "",
      "ScrollbarDownButtonAssetId": "",
      "InputValueKind": "Text",
      "IsPasswordInput": false,
      "InputLineMode": "SingleLine",
      "InputMaxLength": 20,
      "HintText": "请输入问题2",
      "DefaultInputText": "",
      "CharacterSlotTexts": [],
      "CharacterPreviewAnimations": [],
      "ServerListItemHeight": 76,
      "ServerListItemSpacing": 10,
      "ServerListPreviewItemCount": 12,
      "ServerListItemDefaultStateStyle": {
        "AssetId": "",
        "BackgroundColor": "",
        "NineSlice": {
          "IsEnabled": false,
          "Left": 0,
          "Top": 0,
          "Right": 0,
          "Bottom": 0
        }
      },
      "ServerListItemSelectedStateStyle": {
        "AssetId": "",
        "BackgroundColor": "",
        "NineSlice": {
          "IsEnabled": false,
          "Left": 0,
          "Top": 0,
          "Right": 0,
          "Bottom": 0
        }
      },
      "ServerListItemDisabledStateStyle": {
        "AssetId": "",
        "BackgroundColor": "",
        "NineSlice": {
          "IsEnabled": false,
          "Left": 0,
          "Top": 0,
          "Right": 0,
          "Bottom": 0
        }
      },
      "ServerListItemElements": [],
      "InventoryGridCellWidth": 0,
      "InventoryGridCellHeight": 0,
      "InventoryGridColumnSpacing": 0,
      "InventoryGridRowSpacing": 0,
      "InventoryGridPaddingLeft": 0,
      "InventoryGridPaddingTop": 0,
      "InventoryGridPaddingRight": 0,
      "InventoryGridPaddingBottom": 0,
      "ContentTemplate": null,
      "ButtonTriggerKind": "SystemEvent",
      "ButtonSystemEvent": "CloseWindow",
      "ButtonScriptId": "",
      "ButtonTargetTemplateId": "",
      "ButtonOpenTargetKind": "ContentTemplate",
      "ButtonTargetFixedScreenId": "Inventory",
      "ButtonDefaultStateStyle": {
        "AssetId": "",
        "NineSlice": {
          "IsEnabled": false,
          "Left": 0,
          "Top": 0,
          "Right": 0,
          "Bottom": 0
        },
        "BackgroundColor": "",
        "HotAreaFeedbackColor": "",
        "HotAreaFeedbackOpacity": null,
        "HotAreaFeedbackFeatherRadius": null
      },
      "ButtonHoverStateStyle": {
        "AssetId": "",
        "NineSlice": {
          "IsEnabled": false,
          "Left": 0,
          "Top": 0,
          "Right": 0,
          "Bottom": 0
        },
        "BackgroundColor": "",
        "HotAreaFeedbackColor": "",
        "HotAreaFeedbackOpacity": null,
        "HotAreaFeedbackFeatherRadius": null
      },
      "ButtonPressedStateStyle": {
        "AssetId": "",
        "NineSlice": {
          "IsEnabled": false,
          "Left": 0,
          "Top": 0,
          "Right": 0,
          "Bottom": 0
        },
        "BackgroundColor": "",
        "HotAreaFeedbackColor": "",
        "HotAreaFeedbackOpacity": null,
        "HotAreaFeedbackFeatherRadius": null
      },
      "ButtonClickAreaX": 0,
      "ButtonClickAreaY": 0,
      "ButtonClickAreaWidth": 0,
      "ButtonClickAreaHeight": 0,
      "ButtonClickAreaCornerRadius": 0,
      "IsVisibleByDefault": true
    },
    {
      "ControlId": "registerAnswer2Input",
      "DisplayName": "答案2输入框",
      "Kind": "Input",
      "X": 1058,
      "Y": 574,
      "Width": 251,
      "Height": 42,
      "Anchor": "TopLeft",
      "IsLockedInEditor": true,
      "ZIndex": 16,
      "DragTargetControlIds": [],
      "MinimapLocalRangeScale": 1,
      "MinimapCompanionControlIds": [],
      "Text": "",
      "FontFamily": "NSimSun",
      "FontSize": 16,
      "TextColor": "#FFFFFF",
      "TextPosition": "TopLeft",
      "IsTextWrapEnabled": false,
      "TextEffect": {
        "IsOutlineEnabled": true,
        "OutlineColor": "#00000080",
        "OutlineWidth": 1,
        "IsShadowEnabled": true,
        "ShadowColor": "#000000",
        "ShadowOffsetX": 1,
        "ShadowOffsetY": 1,
        "ShadowBlur": 0
      },
      "AssetId": "",
      "AssetIds": [],
      "ImageFramesPerSecond": 4,
      "ImageFillMode": "Fit",
      "ImageNineSlice": {
        "IsEnabled": false,
        "Left": 0,
        "Top": 0,
        "Right": 0,
        "Bottom": 0
      },
      "ResourceValueKind": "None",
      "ResourceFillMode": "VerticalOrb",
      "ResourcePreviewRatio": 0.75,
      "BackgroundColor": "#10182099",
      "InputBorderColor": "#7A8994",
      "InputBorderWidth": 1,
      "InputCornerRadius": 6,
      "InputCaretColor": "#DABE6CE6",
      "InputTextOffsetX": 0,
      "InputTextOffsetY": 0,
      "InputCaretOffsetX": 0,
      "InputCaretOffsetY": 0,
      "CanHaveScrollbar": false,
      "ScrollTargetControlId": "",
      "ScrollbarButtonHeight": 18,
      "ScrollbarMinimumThumbHeight": 24,
      "ScrollbarTrackColor": "#0C1520CC",
      "ScrollbarThumbColor": "#7A8994",
      "ScrollbarButtonColor": "#223344CC",
      "ScrollbarTrackAssetId": "",
      "ScrollbarThumbAssetId": "",
      "ScrollbarUpButtonAssetId": "",
      "ScrollbarDownButtonAssetId": "",
      "InputValueKind": "Text",
      "IsPasswordInput": false,
      "InputLineMode": "SingleLine",
      "InputMaxLength": 20,
      "HintText": "请输入答案2",
      "DefaultInputText": "",
      "CharacterSlotTexts": [],
      "CharacterPreviewAnimations": [],
      "ServerListItemHeight": 76,
      "ServerListItemSpacing": 10,
      "ServerListPreviewItemCount": 12,
      "ServerListItemDefaultStateStyle": {
        "AssetId": "",
        "BackgroundColor": "",
        "NineSlice": {
          "IsEnabled": false,
          "Left": 0,
          "Top": 0,
          "Right": 0,
          "Bottom": 0
        }
      },
      "ServerListItemSelectedStateStyle": {
        "AssetId": "",
        "BackgroundColor": "",
        "NineSlice": {
          "IsEnabled": false,
          "Left": 0,
          "Top": 0,
          "Right": 0,
          "Bottom": 0
        }
      },
      "ServerListItemDisabledStateStyle": {
        "AssetId": "",
        "BackgroundColor": "",
        "NineSlice": {
          "IsEnabled": false,
          "Left": 0,
          "Top": 0,
          "Right": 0,
          "Bottom": 0
        }
      },
      "ServerListItemElements": [],
      "InventoryGridCellWidth": 0,
      "InventoryGridCellHeight": 0,
      "InventoryGridColumnSpacing": 0,
      "InventoryGridRowSpacing": 0,
      "InventoryGridPaddingLeft": 0,
      "InventoryGridPaddingTop": 0,
      "InventoryGridPaddingRight": 0,
      "InventoryGridPaddingBottom": 0,
      "ContentTemplate": null,
      "ButtonTriggerKind": "SystemEvent",
      "ButtonSystemEvent": "CloseWindow",
      "ButtonScriptId": "",
      "ButtonTargetTemplateId": "",
      "ButtonOpenTargetKind": "ContentTemplate",
      "ButtonTargetFixedScreenId": "Inventory",
      "ButtonDefaultStateStyle": {
        "AssetId": "",
        "NineSlice": {
          "IsEnabled": false,
          "Left": 0,
          "Top": 0,
          "Right": 0,
          "Bottom": 0
        },
        "BackgroundColor": "",
        "HotAreaFeedbackColor": "",
        "HotAreaFeedbackOpacity": null,
        "HotAreaFeedbackFeatherRadius": null
      },
      "ButtonHoverStateStyle": {
        "AssetId": "",
        "NineSlice": {
          "IsEnabled": false,
          "Left": 0,
          "Top": 0,
          "Right": 0,
          "Bottom": 0
        },
        "BackgroundColor": "",
        "HotAreaFeedbackColor": "",
        "HotAreaFeedbackOpacity": null,
        "HotAreaFeedbackFeatherRadius": null
      },
      "ButtonPressedStateStyle": {
        "AssetId": "",
        "NineSlice": {
          "IsEnabled": false,
          "Left": 0,
          "Top": 0,
          "Right": 0,
          "Bottom": 0
        },
        "BackgroundColor": "",
        "HotAreaFeedbackColor": "",
        "HotAreaFeedbackOpacity": null,
        "HotAreaFeedbackFeatherRadius": null
      },
      "ButtonClickAreaX": 0,
      "ButtonClickAreaY": 0,
      "ButtonClickAreaWidth": 0,
      "ButtonClickAreaHeight": 0,
      "ButtonClickAreaCornerRadius": 0,
      "IsVisibleByDefault": true
    },
    {
      "ControlId": "registerSubmitButton",
      "DisplayName": "注册按钮",
      "Kind": "Button",
      "X": 631,
      "Y": 696,
      "Width": 281,
      "Height": 50,
      "Anchor": "TopLeft",
      "IsLockedInEditor": true,
      "ZIndex": 17,
      "DragTargetControlIds": [],
      "MinimapLocalRangeScale": 1,
      "MinimapCompanionControlIds": [],
      "Text": "",
      "FontFamily": "NSimSun",
      "FontSize": 16,
      "TextColor": "#FFFFFF",
      "TextPosition": "MiddleCenter",
      "IsTextWrapEnabled": false,
      "TextEffect": {
        "IsOutlineEnabled": true,
        "OutlineColor": "#00000080",
        "OutlineWidth": 1,
        "IsShadowEnabled": true,
        "ShadowColor": "#000000",
        "ShadowOffsetX": 1,
        "ShadowOffsetY": 1,
        "ShadowBlur": 0
      },
      "AssetId": "",
      "AssetIds": [],
      "ImageFramesPerSecond": 4,
      "ImageFillMode": "Fit",
      "ImageNineSlice": {
        "IsEnabled": false,
        "Left": 0,
        "Top": 0,
        "Right": 0,
        "Bottom": 0
      },
      "ResourceValueKind": "None",
      "ResourceFillMode": "VerticalOrb",
      "ResourcePreviewRatio": 0.75,
      "BackgroundColor": "",
      "InputBorderColor": "#7A8994",
      "InputBorderWidth": 1,
      "InputCornerRadius": 6,
      "InputCaretColor": "#DABE6CE6",
      "InputTextOffsetX": 0,
      "InputTextOffsetY": 0,
      "InputCaretOffsetX": 0,
      "InputCaretOffsetY": 0,
      "CanHaveScrollbar": false,
      "ScrollTargetControlId": "",
      "ScrollbarButtonHeight": 18,
      "ScrollbarMinimumThumbHeight": 24,
      "ScrollbarTrackColor": "#0C1520CC",
      "ScrollbarThumbColor": "#7A8994",
      "ScrollbarButtonColor": "#223344CC",
      "ScrollbarTrackAssetId": "",
      "ScrollbarThumbAssetId": "",
      "ScrollbarUpButtonAssetId": "",
      "ScrollbarDownButtonAssetId": "",
      "InputValueKind": "Text",
      "IsPasswordInput": false,
      "InputLineMode": "SingleLine",
      "InputMaxLength": 20,
      "HintText": "",
      "DefaultInputText": "",
      "CharacterSlotTexts": [],
      "CharacterPreviewAnimations": [],
      "ServerListItemHeight": 76,
      "ServerListItemSpacing": 10,
      "ServerListPreviewItemCount": 12,
      "ServerListItemDefaultStateStyle": {
        "AssetId": "",
        "BackgroundColor": "",
        "NineSlice": {
          "IsEnabled": false,
          "Left": 0,
          "Top": 0,
          "Right": 0,
          "Bottom": 0
        }
      },
      "ServerListItemSelectedStateStyle": {
        "AssetId": "",
        "BackgroundColor": "",
        "NineSlice": {
          "IsEnabled": false,
          "Left": 0,
          "Top": 0,
          "Right": 0,
          "Bottom": 0
        }
      },
      "ServerListItemDisabledStateStyle": {
        "AssetId": "",
        "BackgroundColor": "",
        "NineSlice": {
          "IsEnabled": false,
          "Left": 0,
          "Top": 0,
          "Right": 0,
          "Bottom": 0
        }
      },
      "ServerListItemElements": [],
      "InventoryGridCellWidth": 0,
      "InventoryGridCellHeight": 0,
      "InventoryGridColumnSpacing": 0,
      "InventoryGridRowSpacing": 0,
      "InventoryGridPaddingLeft": 0,
      "InventoryGridPaddingTop": 0,
      "InventoryGridPaddingRight": 0,
      "InventoryGridPaddingBottom": 0,
      "ContentTemplate": null,
      "ButtonTriggerKind": "SystemEvent",
      "ButtonSystemEvent": "Register",
      "ButtonScriptId": "",
      "ButtonTargetTemplateId": "",
      "ButtonOpenTargetKind": "ContentTemplate",
      "ButtonTargetFixedScreenId": "Inventory",
      "ButtonDefaultStateStyle": {
        "AssetId": "",
        "NineSlice": {
          "IsEnabled": false,
          "Left": 0,
          "Top": 0,
          "Right": 0,
          "Bottom": 0
        },
        "BackgroundColor": "",
        "HotAreaFeedbackColor": "",
        "HotAreaFeedbackOpacity": null,
        "HotAreaFeedbackFeatherRadius": null
      },
      "ButtonHoverStateStyle": {
        "AssetId": "",
        "NineSlice": {
          "IsEnabled": false,
          "Left": 0,
          "Top": 0,
          "Right": 0,
          "Bottom": 0
        },
        "BackgroundColor": "",
        "HotAreaFeedbackColor": "#00000080",
        "HotAreaFeedbackOpacity": 0.5,
        "HotAreaFeedbackFeatherRadius": null
      },
      "ButtonPressedStateStyle": {
        "AssetId": "",
        "NineSlice": {
          "IsEnabled": false,
          "Left": 0,
          "Top": 0,
          "Right": 0,
          "Bottom": 0
        },
        "BackgroundColor": "",
        "HotAreaFeedbackColor": "",
        "HotAreaFeedbackOpacity": null,
        "HotAreaFeedbackFeatherRadius": null
      },
      "ButtonClickAreaX": 0,
      "ButtonClickAreaY": 0,
      "ButtonClickAreaWidth": 281,
      "ButtonClickAreaHeight": 50,
      "ButtonClickAreaCornerRadius": 0,
      "IsVisibleByDefault": true
    },
    {
      "ControlId": "registerBackButton",
      "DisplayName": "返回按钮",
      "Kind": "Button",
      "X": 944,
      "Y": 700,
      "Width": 273,
      "Height": 43,
      "Anchor": "TopLeft",
      "IsLockedInEditor": true,
      "ZIndex": 18,
      "DragTargetControlIds": [],
      "MinimapLocalRangeScale": 1,
      "MinimapCompanionControlIds": [],
      "Text": "",
      "FontFamily": "NSimSun",
      "FontSize": 16,
      "TextColor": "#FFFFFF",
      "TextPosition": "MiddleCenter",
      "IsTextWrapEnabled": false,
      "TextEffect": {
        "IsOutlineEnabled": true,
        "OutlineColor": "#00000080",
        "OutlineWidth": 1,
        "IsShadowEnabled": true,
        "ShadowColor": "#000000",
        "ShadowOffsetX": 1,
        "ShadowOffsetY": 1,
        "ShadowBlur": 0
      },
      "AssetId": "",
      "AssetIds": [],
      "ImageFramesPerSecond": 4,
      "ImageFillMode": "Fit",
      "ImageNineSlice": {
        "IsEnabled": false,
        "Left": 0,
        "Top": 0,
        "Right": 0,
        "Bottom": 0
      },
      "ResourceValueKind": "None",
      "ResourceFillMode": "VerticalOrb",
      "ResourcePreviewRatio": 0.75,
      "BackgroundColor": "",
      "InputBorderColor": "#7A8994",
      "InputBorderWidth": 1,
      "InputCornerRadius": 6,
      "InputCaretColor": "#DABE6CE6",
      "InputTextOffsetX": 0,
      "InputTextOffsetY": 0,
      "InputCaretOffsetX": 0,
      "InputCaretOffsetY": 0,
      "CanHaveScrollbar": false,
      "ScrollTargetControlId": "",
      "ScrollbarButtonHeight": 18,
      "ScrollbarMinimumThumbHeight": 24,
      "ScrollbarTrackColor": "#0C1520CC",
      "ScrollbarThumbColor": "#7A8994",
      "ScrollbarButtonColor": "#223344CC",
      "ScrollbarTrackAssetId": "",
      "ScrollbarThumbAssetId": "",
      "ScrollbarUpButtonAssetId": "",
      "ScrollbarDownButtonAssetId": "",
      "InputValueKind": "Text",
      "IsPasswordInput": false,
      "InputLineMode": "SingleLine",
      "InputMaxLength": 20,
      "HintText": "",
      "DefaultInputText": "",
      "CharacterSlotTexts": [],
      "CharacterPreviewAnimations": [],
      "ServerListItemHeight": 76,
      "ServerListItemSpacing": 10,
      "ServerListPreviewItemCount": 12,
      "ServerListItemDefaultStateStyle": {
        "AssetId": "",
        "BackgroundColor": "",
        "NineSlice": {
          "IsEnabled": false,
          "Left": 0,
          "Top": 0,
          "Right": 0,
          "Bottom": 0
        }
      },
      "ServerListItemSelectedStateStyle": {
        "AssetId": "",
        "BackgroundColor": "",
        "NineSlice": {
          "IsEnabled": false,
          "Left": 0,
          "Top": 0,
          "Right": 0,
          "Bottom": 0
        }
      },
      "ServerListItemDisabledStateStyle": {
        "AssetId": "",
        "BackgroundColor": "",
        "NineSlice": {
          "IsEnabled": false,
          "Left": 0,
          "Top": 0,
          "Right": 0,
          "Bottom": 0
        }
      },
      "ServerListItemElements": [],
      "InventoryGridCellWidth": 0,
      "InventoryGridCellHeight": 0,
      "InventoryGridColumnSpacing": 0,
      "InventoryGridRowSpacing": 0,
      "InventoryGridPaddingLeft": 0,
      "InventoryGridPaddingTop": 0,
      "InventoryGridPaddingRight": 0,
      "InventoryGridPaddingBottom": 0,
      "ContentTemplate": null,
      "ButtonTriggerKind": "SystemEvent",
      "ButtonSystemEvent": "CloseWindow",
      "ButtonScriptId": "",
      "ButtonTargetTemplateId": "",
      "ButtonOpenTargetKind": "ContentTemplate",
      "ButtonTargetFixedScreenId": "Inventory",
      "ButtonDefaultStateStyle": {
        "AssetId": "",
        "NineSlice": {
          "IsEnabled": false,
          "Left": 0,
          "Top": 0,
          "Right": 0,
          "Bottom": 0
        },
        "BackgroundColor": "",
        "HotAreaFeedbackColor": "",
        "HotAreaFeedbackOpacity": null,
        "HotAreaFeedbackFeatherRadius": null
      },
      "ButtonHoverStateStyle": {
        "AssetId": "",
        "NineSlice": {
          "IsEnabled": false,
          "Left": 0,
          "Top": 0,
          "Right": 0,
          "Bottom": 0
        },
        "BackgroundColor": "",
        "HotAreaFeedbackColor": "#00000080",
        "HotAreaFeedbackOpacity": 0.5,
        "HotAreaFeedbackFeatherRadius": null
      },
      "ButtonPressedStateStyle": {
        "AssetId": "",
        "NineSlice": {
          "IsEnabled": false,
          "Left": 0,
          "Top": 0,
          "Right": 0,
          "Bottom": 0
        },
        "BackgroundColor": "",
        "HotAreaFeedbackColor": "",
        "HotAreaFeedbackOpacity": null,
        "HotAreaFeedbackFeatherRadius": null
      },
      "ButtonClickAreaX": 0,
      "ButtonClickAreaY": 0,
      "ButtonClickAreaWidth": 273,
      "ButtonClickAreaHeight": 43,
      "ButtonClickAreaCornerRadius": 0,
      "IsVisibleByDefault": true
    }
  ]
}